{"sections":{"hero_k3FHft":{"type":"hero","blocks":{"text_NjYHUz":{"type":"text","name":"t:names.heading","settings":{"text":"<h2>Guided by Nature <\/h2><h2>Perfected by Science<\/h2>","width":"fit-content","max_width":"normal","alignment":"left","type_preset":"rte","font":"var(--font-body--family)","font_size":"1rem","line_height":"normal","letter_spacing":"normal","case":"none","wrap":"pretty","color":"var(--color-foreground)","background":true,"background_color":"#00000026","corner_radius":9,"padding-block-start":0,"padding-block-end":0,"padding-inline-start":0,"padding-inline-end":0},"blocks":{}},"group_caCRTd":{"type":"group","name":"t:names.group","settings":{"content_direction":"column","vertical_on_mobile":true,"horizontal_alignment":"flex-start","vertical_alignment":"center","align_baseline":false,"horizontal_alignment_flex_direction_column":"flex-start","vertical_alignment_flex_direction_column":"center","gap":12,"width":"fill","custom_width":100,"width_mobile":"fill","custom_width_mobile":100,"height":"fit","custom_height":100,"inherit_color_scheme":true,"color_scheme":"","background_media":"none","video_position":"cover","background_image_position":"cover","border":"none","border_width":1,"border_opacity":100,"border_radius":0,"toggle_overlay":false,"overlay_color":"#00000026","overlay_style":"solid","gradient_direction":"to top","link":"","open_in_new_tab":false,"placeholder":"","padding-block-start":0,"padding-block-end":0,"padding-inline-start":0,"padding-inline-end":0},"blocks":{"text_YKAVM3":{"type":"text","name":"t:names.text","settings":{"text":"<ul><li><strong>Doctor-formulated for real blood sugar control<\/strong><\/li><li><strong>Supports steady energy and metabolic balance<\/strong><\/li><li><strong>Simple daily routine with long-term result<\/strong><\/li><\/ul>","width":"fit-content","max_width":"normal","alignment":"left","type_preset":"rte","font":"var(--font-body--family)","font_size":"1rem","line_height":"normal","letter_spacing":"normal","case":"none","wrap":"pretty","color":"var(--color-foreground)","background":true,"background_color":"#ffffff14","corner_radius":0,"padding-block-start":0,"padding-block-end":0,"padding-inline-start":0,"padding-inline-end":0},"blocks":{}}},"block_order":["text_YKAVM3"]},"button_hPDbUN":{"type":"button","name":"t:names.button","settings":{"label":"Shop now","link":"shopify:\/\/collections\/all","open_in_new_tab":false,"style_class":"button","width":"fit-content","custom_width":100,"width_mobile":"fit-content","custom_width_mobile":100},"blocks":{}}},"block_order":["text_NjYHUz","group_caCRTd","button_hPDbUN"],"name":"t:names.hero","settings":{"media_type_1":"image","image_1":"shopify:\/\/shop_images\/images_1_e0d29a3e-1243-444a-bdb0-a8b7bad13ed7.jpg","media_type_2":"image","stack_media_on_mobile":false,"custom_mobile_media":false,"media_type_1_mobile":"image","media_type_2_mobile":"image","link":"","open_in_new_tab":false,"content_direction":"column","vertical_on_mobile":true,"horizontal_alignment":"flex-start","vertical_alignment":"center","align_baseline":false,"horizontal_alignment_flex_direction_column":"flex-start","vertical_alignment_flex_direction_column":"center","gap":13,"section_width":"page-width","section_height":"custom","section_height_custom":28,"color_scheme":"scheme-1","toggle_overlay":true,"overlay_color":"#00000026","overlay_style":"gradient","gradient_direction":"to top","blurred_reflection":false,"reflection_opacity":75,"padding-block-start":40,"padding-block-end":57}},"main":{"type":"main-collection","blocks":{"filters":{"type":"filters","static":true,"settings":{"enable_filtering":true,"filter_style":"horizontal","filter_width":"centered","text_label_case":"default","show_swatch_label":false,"show_filter_label":false,"enable_sorting":true,"enable_grid_density":true,"inherit_color_scheme":true,"color_scheme":"","padding-block-start":8,"padding-block-end":8,"padding-inline-start":0,"padding-inline-end":0,"facets_margin_bottom":8,"facets_margin_right":20},"blocks":{}},"product-card":{"type":"_product-card","static":true,"settings":{"product_card_gap":4,"inherit_color_scheme":true,"color_scheme":"","border":"none","border_width":1,"border_opacity":100,"border_radius":0,"padding-block-start":0,"padding-block-end":0,"padding-inline-start":0,"padding-inline-end":0},"blocks":{"card-gallery":{"type":"_product-card-gallery","settings":{"image_ratio":"adapt","border":"none","border_width":1,"border_opacity":100,"border_radius":0,"padding-block-start":0,"padding-block-end":0,"padding-inline-start":0,"padding-inline-end":0},"blocks":{}},"product_title_4nY4eT":{"type":"product-title","name":"t:names.product_title","settings":{"width":"100%","max_width":"normal","alignment":"left","type_preset":"rte","font":"var(--font-body--family)","font_size":"1rem","line_height":"normal","letter_spacing":"normal","case":"none","wrap":"pretty","color":"var(--color-foreground)","background":false,"background_color":"#00000026","corner_radius":0,"padding-block-start":4,"padding-block-end":0,"padding-inline-start":0,"padding-inline-end":0},"blocks":{}},"price_EzJzMm":{"type":"price","settings":{"show_sale_price_first":true,"show_installments":false,"show_tax_info":false,"type_preset":"h6","width":"100%","alignment":"left","font":"var(--font-body--family)","font_size":"1rem","line_height":"normal","letter_spacing":"normal","case":"none","color":"var(--color-foreground)","padding-block-start":0,"padding-block-end":0,"padding-inline-start":0,"padding-inline-end":0},"blocks":{}}},"block_order":["card-gallery","product_title_4nY4eT","price_EzJzMm"]}},"disabled":true,"settings":{"layout_type":"grid","product_card_size":"medium","mobile_product_card_size":"small","enable_infinite_scroll":true,"products_per_page":24,"product_grid_width":"centered","full_width_on_mobile":true,"columns_gap_horizontal":16,"columns_gap_vertical":24,"padding-inline-start":0,"padding-inline-end":0,"color_scheme":"scheme-1","padding-block-start":0,"padding-block-end":32}},"section_UH4fzD":{"type":"section","blocks":{"group_BQdETq":{"type":"group","name":"t:names.group","settings":{"content_direction":"row","vertical_on_mobile":true,"horizontal_alignment":"flex-start","vertical_alignment":"center","align_baseline":false,"horizontal_alignment_flex_direction_column":"center","vertical_alignment_flex_direction_column":"center","gap":12,"width":"fill","custom_width":100,"width_mobile":"fill","custom_width_mobile":100,"height":"fit","custom_height":100,"inherit_color_scheme":true,"color_scheme":"","background_media":"none","video_position":"cover","background_image_position":"cover","border":"none","border_width":1,"border_opacity":100,"border_radius":0,"toggle_overlay":false,"overlay_color":"#00000026","overlay_style":"solid","gradient_direction":"to top","link":"","open_in_new_tab":false,"placeholder":"","padding-block-start":0,"padding-block-end":0,"padding-inline-start":0,"padding-inline-end":0},"blocks":{"text_kNxtnd":{"type":"text","name":"t:names.heading","settings":{"text":"<h2>Impurity Free<\/h2>","width":"fit-content","max_width":"normal","alignment":"left","type_preset":"h4","font":"var(--font-body--family)","font_size":"1rem","line_height":"normal","letter_spacing":"normal","case":"none","wrap":"pretty","color":"var(--color-foreground)","background":false,"background_color":"#00000026","corner_radius":0,"padding-block-start":0,"padding-block-end":0,"padding-inline-start":0,"padding-inline-end":0},"blocks":{}},"text_yhP6NB":{"type":"text","name":"t:names.heading","settings":{"text":"<h2>Doctor-Formulated<\/h2>","width":"fit-content","max_width":"normal","alignment":"left","type_preset":"h4","font":"var(--font-body--family)","font_size":"1rem","line_height":"normal","letter_spacing":"normal","case":"none","wrap":"pretty","color":"var(--color-foreground)","background":false,"background_color":"#00000026","corner_radius":0,"padding-block-start":0,"padding-block-end":0,"padding-inline-start":0,"padding-inline-end":0},"blocks":{}},"text_9xJeTP":{"type":"text","name":"t:names.heading","settings":{"text":"<h2>Plant-Based Formulation<\/h2>","width":"fit-content","max_width":"normal","alignment":"left","type_preset":"h4","font":"var(--font-body--family)","font_size":"1rem","line_height":"normal","letter_spacing":"normal","case":"none","wrap":"pretty","color":"var(--color-foreground)","background":false,"background_color":"#00000026","corner_radius":0,"padding-block-start":0,"padding-block-end":0,"padding-inline-start":0,"padding-inline-end":0},"blocks":{}},"text_bTXpFL":{"type":"text","name":"t:names.heading","settings":{"text":"<h2>Expert-Formulation<\/h2>","width":"fit-content","max_width":"normal","alignment":"left","type_preset":"h4","font":"var(--font-body--family)","font_size":"1rem","line_height":"normal","letter_spacing":"normal","case":"none","wrap":"pretty","color":"var(--color-foreground)","background":false,"background_color":"#00000026","corner_radius":0,"padding-block-start":0,"padding-block-end":0,"padding-inline-start":0,"padding-inline-end":0},"blocks":{}},"text_9zDi8b":{"type":"text","name":"t:names.heading","settings":{"text":"<h2>Lab-Tested<\/h2>","width":"fit-content","max_width":"normal","alignment":"left","type_preset":"h4","font":"var(--font-body--family)","font_size":"1rem","line_height":"normal","letter_spacing":"normal","case":"none","wrap":"pretty","color":"var(--color-foreground)","background":false,"background_color":"#00000026","corner_radius":0,"padding-block-start":0,"padding-block-end":0,"padding-inline-start":0,"padding-inline-end":0},"blocks":{}}},"block_order":["text_kNxtnd","text_yhP6NB","text_9xJeTP","text_bTXpFL","text_9zDi8b"]}},"block_order":["group_BQdETq"],"name":"S2- heading","settings":{"content_direction":"column","vertical_on_mobile":true,"horizontal_alignment":"flex-start","vertical_alignment":"center","align_baseline":false,"horizontal_alignment_flex_direction_column":"center","vertical_alignment_flex_direction_column":"center","gap":30,"section_width":"page-width","section_height":"medium","section_height_custom":50,"color_scheme":"scheme-5","background_media":"none","video_position":"cover","background_image_position":"cover","border":"none","border_width":1,"border_opacity":100,"border_radius":0,"toggle_overlay":false,"overlay_color":"#00000026","overlay_style":"solid","gradient_direction":"to top","padding-block-start":0,"padding-block-end":0}},"section_CRAWEN":{"type":"section","blocks":{"text_WiqzrT":{"type":"text","name":"t:names.heading","settings":{"text":"<h2>Best Seller<\/h2>","width":"fit-content","max_width":"normal","alignment":"left","type_preset":"rte","font":"var(--font-body--family)","font_size":"1rem","line_height":"normal","letter_spacing":"normal","case":"none","wrap":"pretty","color":"var(--color-foreground)","background":false,"background_color":"#00000026","corner_radius":0,"padding-block-start":0,"padding-block-end":0,"padding-inline-start":0,"padding-inline-end":0},"blocks":{}},"group_FRiKXw":{"type":"group","name":"t:names.group","settings":{"content_direction":"row","vertical_on_mobile":true,"horizontal_alignment":"center","vertical_alignment":"center","align_baseline":false,"horizontal_alignment_flex_direction_column":"flex-start","vertical_alignment_flex_direction_column":"center","gap":81,"width":"fill","custom_width":100,"width_mobile":"fill","custom_width_mobile":100,"height":"fit","custom_height":100,"inherit_color_scheme":true,"color_scheme":"","background_media":"none","video_position":"cover","background_image_position":"cover","border":"none","border_width":1,"border_opacity":100,"border_radius":7,"toggle_overlay":false,"overlay_color":"#00000026","overlay_style":"solid","gradient_direction":"to top","link":"","open_in_new_tab":false,"placeholder":"","padding-block-start":22,"padding-block-end":17,"padding-inline-start":0,"padding-inline-end":0},"blocks":{"text_4BHxJz":{"type":"text","name":"t:names.text","settings":{"text":"<p>Tested Lab by Purity<\/p>","width":"fit-content","max_width":"normal","alignment":"left","type_preset":"rte","font":"var(--font-body--family)","font_size":"1rem","line_height":"normal","letter_spacing":"normal","case":"none","wrap":"pretty","color":"var(--color-foreground)","background":false,"background_color":"#00000026","corner_radius":0,"padding-block-start":0,"padding-block-end":0,"padding-inline-start":0,"padding-inline-end":0},"blocks":{}},"text_TfNrkc":{"type":"text","name":"t:names.text","settings":{"text":"<p>Expert Formulated<\/p>","width":"fit-content","max_width":"normal","alignment":"left","type_preset":"rte","font":"var(--font-body--family)","font_size":"1rem","line_height":"normal","letter_spacing":"normal","case":"none","wrap":"pretty","color":"var(--color-foreground)","background":false,"background_color":"#00000026","corner_radius":0,"padding-block-start":0,"padding-block-end":0,"padding-inline-start":0,"padding-inline-end":0},"blocks":{}},"text_r4jRjT":{"type":"text","name":"t:names.text","settings":{"text":"<p>Impurity Free<\/p>","width":"fit-content","max_width":"normal","alignment":"left","type_preset":"rte","font":"var(--font-body--family)","font_size":"1rem","line_height":"normal","letter_spacing":"normal","case":"none","wrap":"pretty","color":"var(--color-foreground)","background":false,"background_color":"#00000026","corner_radius":0,"padding-block-start":0,"padding-block-end":0,"padding-inline-start":0,"padding-inline-end":0},"blocks":{}}},"block_order":["text_4BHxJz","text_TfNrkc","text_r4jRjT"]},"group_Pk7pX8":{"type":"group","name":"t:names.group","settings":{"content_direction":"row","vertical_on_mobile":true,"horizontal_alignment":"center","vertical_alignment":"center","align_baseline":false,"horizontal_alignment_flex_direction_column":"flex-start","vertical_alignment_flex_direction_column":"center","gap":43,"width":"fill","custom_width":100,"width_mobile":"fill","custom_width_mobile":100,"height":"fit","custom_height":100,"inherit_color_scheme":true,"color_scheme":"","background_media":"none","video_position":"cover","background_image_position":"cover","border":"none","border_width":1,"border_opacity":100,"border_radius":0,"toggle_overlay":false,"overlay_color":"#00000026","overlay_style":"solid","gradient_direction":"to top","link":"","open_in_new_tab":false,"placeholder":"","padding-block-start":0,"padding-block-end":0,"padding-inline-start":0,"padding-inline-end":0},"blocks":{"button_yNxWkn":{"type":"button","name":"t:names.button","settings":{"label":"Best Seller","link":"shopify:\/\/collections\/all","open_in_new_tab":false,"style_class":"button","width":"fit-content","custom_width":100,"width_mobile":"fit-content","custom_width_mobile":100},"blocks":{}},"button_UawWwA":{"type":"button","name":"t:names.button","settings":{"label":"Shop now","link":"shopify:\/\/collections\/all","open_in_new_tab":false,"style_class":"button","width":"fit-content","custom_width":100,"width_mobile":"fit-content","custom_width_mobile":100},"blocks":{}},"button_aDz3yw":{"type":"button","name":"t:names.button","settings":{"label":"Shop now","link":"shopify:\/\/collections\/all","open_in_new_tab":false,"style_class":"button","width":"fit-content","custom_width":100,"width_mobile":"fit-content","custom_width_mobile":100},"blocks":{}},"button_fNMYPV":{"type":"button","name":"t:names.button","settings":{"label":"Shop now","link":"shopify:\/\/collections\/all","open_in_new_tab":false,"style_class":"button","width":"fit-content","custom_width":100,"width_mobile":"fit-content","custom_width_mobile":100},"blocks":{}},"button_jDDDMb":{"type":"button","name":"t:names.button","settings":{"label":"Shop now","link":"shopify:\/\/collections\/all","open_in_new_tab":false,"style_class":"button","width":"fit-content","custom_width":100,"width_mobile":"fit-content","custom_width_mobile":100},"blocks":{}}},"block_order":["button_yNxWkn","button_UawWwA","button_aDz3yw","button_fNMYPV","button_jDDDMb"]}},"block_order":["text_WiqzrT","group_FRiKXw","group_Pk7pX8"],"name":"S3- Best Seller","settings":{"content_direction":"column","vertical_on_mobile":true,"horizontal_alignment":"flex-start","vertical_alignment":"center","align_baseline":false,"horizontal_alignment_flex_direction_column":"center","vertical_alignment_flex_direction_column":"center","gap":12,"section_width":"page-width","section_height":"small","section_height_custom":50,"color_scheme":"scheme-1","background_media":"none","video_position":"cover","background_image_position":"cover","border":"none","border_width":1,"border_opacity":100,"border_radius":0,"toggle_overlay":false,"overlay_color":"#00000026","overlay_style":"solid","gradient_direction":"to top","padding-block-start":0,"padding-block-end":0}},"section_ak6nNd":{"type":"section","blocks":{"group_r7fUTP":{"type":"group","name":"t:names.group","settings":{"content_direction":"column","vertical_on_mobile":true,"horizontal_alignment":"flex-start","vertical_alignment":"center","align_baseline":false,"horizontal_alignment_flex_direction_column":"flex-start","vertical_alignment_flex_direction_column":"center","gap":12,"width":"fill","custom_width":100,"width_mobile":"fill","custom_width_mobile":100,"height":"fit","custom_height":100,"inherit_color_scheme":true,"color_scheme":"","background_media":"none","video_position":"cover","background_image_position":"cover","border":"none","border_width":1,"border_opacity":100,"border_radius":0,"toggle_overlay":false,"overlay_color":"#00000026","overlay_style":"solid","gradient_direction":"to top","link":"","open_in_new_tab":false,"placeholder":"","padding-block-start":0,"padding-block-end":0,"padding-inline-start":0,"padding-inline-end":0},"blocks":{"image_P9UBB3":{"type":"image","name":"t:names.image","settings":{"image":"shopify:\/\/shop_images\/2_med.jpg","link":"","image_ratio":"portrait","width":"custom","custom_width":85,"width_mobile":"custom","custom_width_mobile":38,"height":"fit","border":"none","border_width":1,"border_opacity":100,"border_radius":51,"padding-block-start":0,"padding-block-end":0,"padding-inline-start":0,"padding-inline-end":0},"blocks":{}},"text_wEFk7x":{"type":"text","name":"t:names.heading","settings":{"text":"<h2>New arrivals<\/h2>","width":"fit-content","max_width":"normal","alignment":"left","type_preset":"rte","font":"var(--font-body--family)","font_size":"1rem","line_height":"normal","letter_spacing":"normal","case":"none","wrap":"pretty","color":"var(--color-foreground)","background":false,"background_color":"#00000026","corner_radius":0,"padding-block-start":0,"padding-block-end":0,"padding-inline-start":0,"padding-inline-end":0},"blocks":{}},"text_BWRUew":{"type":"text","name":"t:names.text","settings":{"text":"<p>We make things that work better and last longer. Our products solve real problems with clean design and honest materials.<\/p>","width":"fit-content","max_width":"normal","alignment":"left","type_preset":"rte","font":"var(--font-body--family)","font_size":"1rem","line_height":"normal","letter_spacing":"normal","case":"none","wrap":"pretty","color":"var(--color-foreground)","background":false,"background_color":"#00000026","corner_radius":0,"padding-block-start":0,"padding-block-end":0,"padding-inline-start":0,"padding-inline-end":0},"blocks":{}},"button_r9VfrA":{"type":"button","name":"t:names.button","settings":{"label":"Shop now","link":"shopify:\/\/collections\/all","open_in_new_tab":false,"style_class":"button","width":"fit-content","custom_width":100,"width_mobile":"fit-content","custom_width_mobile":100},"blocks":{}}},"block_order":["image_P9UBB3","text_wEFk7x","text_BWRUew","button_r9VfrA"]},"group_YewmYj":{"type":"group","name":"t:names.group","settings":{"content_direction":"column","vertical_on_mobile":true,"horizontal_alignment":"flex-start","vertical_alignment":"center","align_baseline":false,"horizontal_alignment_flex_direction_column":"flex-start","vertical_alignment_flex_direction_column":"center","gap":34,"width":"fill","custom_width":100,"width_mobile":"fill","custom_width_mobile":100,"height":"fit","custom_height":100,"inherit_color_scheme":true,"color_scheme":"","background_media":"none","video_position":"cover","background_image_position":"cover","border":"none","border_width":1,"border_opacity":100,"border_radius":0,"toggle_overlay":false,"overlay_color":"#00000026","overlay_style":"solid","gradient_direction":"to top","link":"","open_in_new_tab":false,"placeholder":"","padding-block-start":0,"padding-block-end":0,"padding-inline-start":0,"padding-inline-end":0},"blocks":{"image_Gk6bUR":{"type":"image","name":"t:names.image","settings":{"image":"shopify:\/\/shop_images\/3_med.jpg","link":"","image_ratio":"portrait","width":"custom","custom_width":85,"width_mobile":"custom","custom_width_mobile":47,"height":"fit","border":"none","border_width":1,"border_opacity":100,"border_radius":49,"padding-block-start":0,"padding-block-end":0,"padding-inline-start":0,"padding-inline-end":0},"blocks":{}},"text_TFqBmV":{"type":"text","name":"t:names.heading","settings":{"text":"<h2>New arrivals<\/h2>","width":"fit-content","max_width":"normal","alignment":"left","type_preset":"rte","font":"var(--font-body--family)","font_size":"1rem","line_height":"normal","letter_spacing":"normal","case":"none","wrap":"pretty","color":"var(--color-foreground)","background":false,"background_color":"#00000026","corner_radius":0,"padding-block-start":0,"padding-block-end":0,"padding-inline-start":0,"padding-inline-end":0},"blocks":{}},"text_zWM3jY":{"type":"text","name":"t:names.text","settings":{"text":"<p>We make things that work better and last longer. Our products solve real problems with clean design and honest materials.<\/p>","width":"fit-content","max_width":"normal","alignment":"left","type_preset":"rte","font":"var(--font-body--family)","font_size":"1rem","line_height":"normal","letter_spacing":"normal","case":"none","wrap":"pretty","color":"var(--color-foreground)","background":false,"background_color":"#00000026","corner_radius":0,"padding-block-start":0,"padding-block-end":0,"padding-inline-start":0,"padding-inline-end":0},"blocks":{}},"button_VtdKcj":{"type":"button","name":"t:names.button","settings":{"label":"Shop now","link":"shopify:\/\/collections\/all","open_in_new_tab":false,"style_class":"button","width":"fit-content","custom_width":100,"width_mobile":"fit-content","custom_width_mobile":100},"blocks":{}}},"block_order":["image_Gk6bUR","text_TFqBmV","text_zWM3jY","button_VtdKcj"]},"group_HQfJpr":{"type":"group","name":"t:names.group","settings":{"content_direction":"column","vertical_on_mobile":true,"horizontal_alignment":"flex-start","vertical_alignment":"center","align_baseline":false,"horizontal_alignment_flex_direction_column":"flex-start","vertical_alignment_flex_direction_column":"center","gap":12,"width":"fill","custom_width":100,"width_mobile":"fill","custom_width_mobile":100,"height":"fit","custom_height":100,"inherit_color_scheme":true,"color_scheme":"","background_media":"none","video_position":"cover","background_image_position":"cover","border":"none","border_width":1,"border_opacity":100,"border_radius":0,"toggle_overlay":false,"overlay_color":"#00000026","overlay_style":"solid","gradient_direction":"to top","link":"","open_in_new_tab":false,"placeholder":"","padding-block-start":0,"padding-block-end":0,"padding-inline-start":0,"padding-inline-end":0},"blocks":{"image_t4jFWf":{"type":"image","name":"t:names.image","settings":{"image":"shopify:\/\/shop_images\/1_Med.jpg","link":"","image_ratio":"portrait","width":"custom","custom_width":85,"width_mobile":"custom","custom_width_mobile":34,"height":"fit","border":"none","border_width":1,"border_opacity":100,"border_radius":53,"padding-block-start":0,"padding-block-end":0,"padding-inline-start":0,"padding-inline-end":0},"blocks":{}},"text_nPTp6G":{"type":"text","name":"t:names.heading","settings":{"text":"<h2>New arrivals<\/h2>","width":"fit-content","max_width":"normal","alignment":"left","type_preset":"rte","font":"var(--font-body--family)","font_size":"1rem","line_height":"normal","letter_spacing":"normal","case":"none","wrap":"pretty","color":"var(--color-foreground)","background":false,"background_color":"#00000026","corner_radius":0,"padding-block-start":0,"padding-block-end":0,"padding-inline-start":0,"padding-inline-end":0},"blocks":{}},"text_m8DkQz":{"type":"text","name":"t:names.text","settings":{"text":"<p>We make things that work better and last longer. Our products solve real problems with clean design and honest materials.<\/p>","width":"fit-content","max_width":"normal","alignment":"left","type_preset":"rte","font":"var(--font-body--family)","font_size":"1rem","line_height":"normal","letter_spacing":"normal","case":"none","wrap":"pretty","color":"var(--color-foreground)","background":false,"background_color":"#00000026","corner_radius":0,"padding-block-start":0,"padding-block-end":0,"padding-inline-start":0,"padding-inline-end":0},"blocks":{}},"button_zgbMGX":{"type":"button","name":"t:names.button","settings":{"label":"Shop now","link":"shopify:\/\/collections\/all","open_in_new_tab":false,"style_class":"button","width":"fit-content","custom_width":100,"width_mobile":"fit-content","custom_width_mobile":100},"blocks":{}}},"block_order":["image_t4jFWf","text_nPTp6G","text_m8DkQz","button_zgbMGX"]}},"block_order":["group_r7fUTP","group_YewmYj","group_HQfJpr"],"name":"t:names.custom_section","settings":{"content_direction":"row","vertical_on_mobile":true,"horizontal_alignment":"flex-start","vertical_alignment":"center","align_baseline":false,"horizontal_alignment_flex_direction_column":"flex-start","vertical_alignment_flex_direction_column":"center","gap":12,"section_width":"page-width","section_height":"small","section_height_custom":50,"color_scheme":"","background_media":"none","video_position":"cover","background_image_position":"cover","border":"none","border_width":1,"border_opacity":100,"border_radius":0,"toggle_overlay":false,"overlay_color":"#00000026","overlay_style":"solid","gradient_direction":"to top","padding-block-start":0,"padding-block-end":0}},"section_md3iyC":{"type":"section","blocks":{"group_C8WAe9":{"type":"group","name":"t:names.group","settings":{"content_direction":"column","vertical_on_mobile":true,"horizontal_alignment":"flex-start","vertical_alignment":"center","align_baseline":false,"horizontal_alignment_flex_direction_column":"flex-start","vertical_alignment_flex_direction_column":"center","gap":12,"width":"fill","custom_width":100,"width_mobile":"fill","custom_width_mobile":100,"height":"fit","custom_height":100,"inherit_color_scheme":true,"color_scheme":"","background_media":"none","video_position":"cover","background_image_position":"cover","border":"none","border_width":1,"border_opacity":100,"border_radius":0,"toggle_overlay":false,"overlay_color":"#00000026","overlay_style":"solid","gradient_direction":"to top","link":"","open_in_new_tab":false,"placeholder":"","padding-block-start":0,"padding-block-end":0,"padding-inline-start":0,"padding-inline-end":0},"blocks":{"text_tR7Czg":{"type":"text","name":"t:names.heading","settings":{"text":"<h2>New arrivals<\/h2>","width":"fit-content","max_width":"normal","alignment":"left","type_preset":"rte","font":"var(--font-body--family)","font_size":"1rem","line_height":"normal","letter_spacing":"normal","case":"none","wrap":"pretty","color":"var(--color-foreground)","background":false,"background_color":"#00000026","corner_radius":0,"padding-block-start":0,"padding-block-end":0,"padding-inline-start":0,"padding-inline-end":0},"blocks":{}}},"block_order":["text_tR7Czg"]},"text_efbHG3":{"type":"text","name":"t:names.text","settings":{"text":"<p>We make things that work better and last longer. Our products solve real problems with clean design and honest materials.<\/p>","width":"fit-content","max_width":"normal","alignment":"left","type_preset":"rte","font":"var(--font-body--family)","font_size":"1rem","line_height":"normal","letter_spacing":"normal","case":"none","wrap":"pretty","color":"var(--color-foreground)","background":false,"background_color":"#00000026","corner_radius":0,"padding-block-start":0,"padding-block-end":0,"padding-inline-start":0,"padding-inline-end":0},"blocks":{}},"button_FiUkBi":{"type":"button","name":"t:names.button","settings":{"label":"Shop now","link":"shopify:\/\/collections\/all","open_in_new_tab":false,"style_class":"button","width":"fit-content","custom_width":100,"width_mobile":"fit-content","custom_width_mobile":100},"blocks":{}},"group_Apwar8":{"type":"group","name":"t:names.group","settings":{"content_direction":"column","vertical_on_mobile":true,"horizontal_alignment":"flex-start","vertical_alignment":"center","align_baseline":false,"horizontal_alignment_flex_direction_column":"flex-start","vertical_alignment_flex_direction_column":"center","gap":12,"width":"fill","custom_width":100,"width_mobile":"fill","custom_width_mobile":100,"height":"fit","custom_height":100,"inherit_color_scheme":true,"color_scheme":"","background_media":"none","video_position":"cover","background_image_position":"cover","border":"none","border_width":1,"border_opacity":100,"border_radius":0,"toggle_overlay":false,"overlay_color":"#00000026","overlay_style":"solid","gradient_direction":"to top","link":"","open_in_new_tab":false,"placeholder":"","padding-block-start":0,"padding-block-end":0,"padding-inline-start":0,"padding-inline-end":0},"blocks":{"image_4jqrkG":{"type":"image","name":"t:names.image","settings":{"image":"shopify:\/\/shop_images\/download_2.jpg","link":"","image_ratio":"square","width":"custom","custom_width":34,"width_mobile":"custom","custom_width_mobile":100,"height":"fit","border":"solid","border_width":5,"border_opacity":100,"border_radius":100,"padding-block-start":0,"padding-block-end":0,"padding-inline-start":0,"padding-inline-end":0},"blocks":{}}},"block_order":["image_4jqrkG"]}},"block_order":["group_C8WAe9","text_efbHG3","button_FiUkBi","group_Apwar8"],"name":"t:names.custom_section","settings":{"content_direction":"column","vertical_on_mobile":true,"horizontal_alignment":"flex-start","vertical_alignment":"center","align_baseline":false,"horizontal_alignment_flex_direction_column":"flex-start","vertical_alignment_flex_direction_column":"center","gap":12,"section_width":"page-width","section_height":"small","section_height_custom":50,"color_scheme":"","background_media":"none","video_position":"cover","background_image_position":"cover","border":"none","border_width":1,"border_opacity":100,"border_radius":0,"toggle_overlay":false,"overlay_color":"#00000026","overlay_style":"solid","gradient_direction":"to top","padding-block-start":0,"padding-block-end":0}}},"order":["hero_k3FHft","main","section_UH4fzD","section_CRAWEN","section_ak6nNd","section_md3iyC"]}